setup.py
gelogus_paket/price_calculation_mod.py
gelogus_paket.egg-info/PKG-INFO
gelogus_paket.egg-info/SOURCES.txt
gelogus_paket.egg-info/dependency_links.txt
gelogus_paket.egg-info/not-zip-safe
gelogus_paket.egg-info/top_level.txt