Metadata-Version: 1.0
Name: gelogus-paket
Version: 0.0
Summary: Пробный пакет для pip
Home-page: UNKNOWN
Author: UNKNOWN
Author-email: gelo2370@mail.ru
License: UNKNOWN
Platform: UNKNOWN
